elemental_tools/__init__.py
elemental_tools/command_line.py
elemental_tools/config.py
elemental_tools/constants.py
elemental_tools/environ.py
elemental_tools/tools.py
elemental_tools/types.py
elemental_tools/Jarvis/__init__.py
elemental_tools/Jarvis/config.py
elemental_tools/Jarvis/exceptions.py
elemental_tools/Jarvis/install.py
elemental_tools/Jarvis/models.py
elemental_tools/Jarvis/brainiac/__init__.py
elemental_tools/Jarvis/brainiac/decorators.py
elemental_tools/Jarvis/brainiac/prediction.py
elemental_tools/Jarvis/grimoires/__init__.py
elemental_tools/Jarvis/grimoires/audio.py
elemental_tools/Jarvis/server/__init__.py
elemental_tools/Jarvis/server/development.py
elemental_tools/Jarvis/server/audio/__init__.py
elemental_tools/Jarvis/server/basic/__init__.py
elemental_tools/Jarvis/server/mercury/__init__.py
elemental_tools/Jarvis/server/whatsapp/__init__.py
elemental_tools/Jarvis/server/whatsapp/api.py
elemental_tools/Jarvis/tools/__init__.py
elemental_tools/Jarvis/tools/translation.py
elemental_tools/Jarvis/tools/web_search.py
elemental_tools/adb/__init__.py
elemental_tools/adb/keymap.py
elemental_tools/api/__init__.py
elemental_tools/api/constants.py
elemental_tools/api/exceptions.py
elemental_tools/api/install.py
elemental_tools/api/settings.py
elemental_tools/api/controllers/__init__.py
elemental_tools/api/controllers/companies.py
elemental_tools/api/controllers/device.py
elemental_tools/api/controllers/institution.py
elemental_tools/api/controllers/notification.py
elemental_tools/api/controllers/smtp.py
elemental_tools/api/controllers/statement.py
elemental_tools/api/controllers/template.py
elemental_tools/api/controllers/transaction.py
elemental_tools/api/controllers/user.py
elemental_tools/api/controllers/webhook.py
elemental_tools/api/controllers/wpp.py
elemental_tools/api/controllers/exceptions/__init__.py
elemental_tools/api/depends/__init__.py
elemental_tools/api/endpoints/__init__.py
elemental_tools/api/endpoints/auth.py
elemental_tools-0.0.6.6.dist-info/licenses/LICENSE
elemental_tools-0.0.6.6.dist-info/METADATA
elemental_tools-0.0.6.6.dist-info/WHEEL
elemental_tools-0.0.6.6.dist-info/entry_points.txt
elemental_tools-0.0.6.6.dist-info/top_level.txt
elemental_tools-0.0.6.6.dist-info/RECORD
